{"moduleDefinition":{"range":[1,1,1,28],"value":{"type":"normal","normal":{"moduleName":{"range":[1,8,1,14],"value":["ThreeD"]},"exposingList":{"range":[1,15,1,28],"value":{"type":"all","all":[1,25,1,27]}}}}},"imports":[{"range":[3,1,3,13],"value":{"moduleName":{"range":[3,8,3,13],"value":["Angle"]},"moduleAlias":null,"exposingList":null}},{"range":[4,1,4,16],"value":{"moduleName":{"range":[4,8,4,16],"value":["Camera3d"]},"moduleAlias":null,"exposingList":null}},{"range":[5,1,5,13],"value":{"moduleName":{"range":[5,8,5,13],"value":["Color"]},"moduleAlias":null,"exposingList":null}},{"range":[6,1,6,19],"value":{"moduleName":{"range":[6,8,6,19],"value":["Direction3d"]},"moduleAlias":null,"exposingList":null}},{"range":[7,1,7,28],"value":{"moduleName":{"range":[7,8,7,12],"value":["Html"]},"moduleAlias":null,"exposingList":{"range":[7,13,7,28],"value":{"type":"explicit","explicit":[{"range":[7,23,7,27],"value":{"type":"typeOrAlias","typeOrAlias":{"name":"Html"}}}]}}}},{"range":[8,1,8,14],"value":{"moduleName":{"range":[8,8,8,14],"value":["Length"]},"moduleAlias":null,"exposingList":null}},{"range":[9,1,9,14],"value":{"moduleName":{"range":[9,8,9,14],"value":["Pixels"]},"moduleAlias":null,"exposingList":null}},{"range":[10,1,10,15],"value":{"moduleName":{"range":[10,8,10,15],"value":["Point3d"]},"moduleAlias":null,"exposingList":null}},{"range":[11,1,11,15],"value":{"moduleName":{"range":[11,8,11,15],"value":["Scene3d"]},"moduleAlias":null,"exposingList":null}},{"range":[12,1,12,36],"value":{"moduleName":{"range":[12,8,12,24],"value":["Scene3d","Material"]},"moduleAlias":{"range":[12,28,12,36],"value":["Material"]},"exposingList":null}},{"range":[13,1,13,19],"value":{"moduleName":{"range":[13,8,13,19],"value":["Viewpoint3d"]},"moduleAlias":null,"exposingList":null}}],"declarations":[{"range":[16,1,39,10],"value":{"type":"function","function":{"documentation":null,"signature":{"range":[16,1,16,16],"value":{"name":{"range":[16,1,16,5],"value":"main"},"typeAnnotation":{"range":[16,8,16,16],"value":{"type":"typed","typed":{"moduleNameAndName":{"range":[16,8,16,12],"value":{"moduleName":[],"name":"Html"}},"args":[{"range":[16,13,16,16],"value":{"type":"generic","generic":{"value":"msg"}}}]}}}}},"declaration":{"range":[17,1,39,10],"value":{"name":{"range":[17,1,17,5],"value":"main"},"arguments":[],"expression":{"range":[18,5,39,10],"value":{"type":"application","application":[{"range":[18,5,18,18],"value":{"type":"functionOrValue","functionOrValue":{"moduleName":["Scene3d"],"name":"unlit"}}},{"range":[19,9,39,10],"value":{"type":"record","record":[{"range":[19,11,25,14],"value":{"field":{"range":[19,11,19,19],"value":"entities"},"expression":{"range":[20,13,25,14],"value":{"type":"list","list":[{"range":[20,15,24,40],"value":{"type":"application","application":[{"range":[20,15,20,27],"value":{"type":"functionOrValue","functionOrValue":{"moduleName":["Scene3d"],"name":"quad"}}},{"range":[20,28,20,55],"value":{"type":"parenthesized","parenthesized":{"range":[20,29,20,54],"value":{"type":"application","application":[{"range":[20,29,20,43],"value":{"type":"functionOrValue","functionOrValue":{"moduleName":["Material"],"name":"color"}}},{"range":[20,44,20,54],"value":{"type":"functionOrValue","functionOrValue":{"moduleName":["Color"],"name":"blue"}}}]}}}},{"range":[21,17,21,41],"value":{"type":"parenthesized","parenthesized":{"range":[21,18,21,40],"value":{"type":"application","application":[{"range":[21,18,21,32],"value":{"type":"functionOrValue","functionOrValue":{"moduleName":["Point3d"],"name":"meters"}}},{"range":[21,33,21,35],"value":{"type":"negation","negation":{"range":[21,34,21,35],"value":{"type":"integer","integer":1}}}},{"range":[21,36,21,38],"value":{"type":"negation","negation":{"range":[21,37,21,38],"value":{"type":"integer","integer":1}}}},{"range":[21,39,21,40],"value":{"type":"integer","integer":0}}]}}}},{"range":[22,17,22,40],"value":{"type":"parenthesized","parenthesized":{"range":[22,18,22,39],"value":{"type":"application","application":[{"range":[22,18,22,32],"value":{"type":"functionOrValue","functionOrValue":{"moduleName":["Point3d"],"name":"meters"}}},{"range":[22,33,22,34],"value":{"type":"integer","integer":1}},{"range":[22,35,22,37],"value":{"type":"negation","negation":{"range":[22,36,22,37],"value":{"type":"integer","integer":1}}}},{"range":[22,38,22,39],"value":{"type":"integer","integer":0}}]}}}},{"range":[23,17,23,39],"value":{"type":"parenthesized","parenthesized":{"range":[23,18,23,38],"value":{"type":"application","application":[{"range":[23,18,23,32],"value":{"type":"functionOrValue","functionOrValue":{"moduleName":["Point3d"],"name":"meters"}}},{"range":[23,33,23,34],"value":{"type":"integer","integer":1}},{"range":[23,35,23,36],"value":{"type":"integer","integer":1}},{"range":[23,37,23,38],"value":{"type":"integer","integer":0}}]}}}},{"range":[24,17,24,40],"value":{"type":"parenthesized","parenthesized":{"range":[24,18,24,39],"value":{"type":"application","application":[{"range":[24,18,24,32],"value":{"type":"functionOrValue","functionOrValue":{"moduleName":["Point3d"],"name":"meters"}}},{"range":[24,33,24,35],"value":{"type":"negation","negation":{"range":[24,34,24,35],"value":{"type":"integer","integer":1}}}},{"range":[24,36,24,37],"value":{"type":"integer","integer":1}},{"range":[24,38,24,39],"value":{"type":"integer","integer":0}}]}}}}]}}]}}}},{"range":[26,11,36,9],"value":{"field":{"range":[26,11,26,17],"value":"camera"},"expression":{"range":[27,13,35,18],"value":{"type":"application","application":[{"range":[27,13,27,33],"value":{"type":"functionOrValue","functionOrValue":{"moduleName":["Camera3d"],"name":"perspective"}}},{"range":[28,17,35,18],"value":{"type":"record","record":[{"range":[28,19,33,26],"value":{"field":{"range":[28,19,28,28],"value":"viewpoint"},"expression":{"range":[29,21,33,26],"value":{"type":"application","application":[{"range":[29,21,29,39],"value":{"type":"functionOrValue","functionOrValue":{"moduleName":["Viewpoint3d"],"name":"lookAt"}}},{"range":[30,25,33,26],"value":{"type":"record","record":[{"range":[30,27,30,54],"value":{"field":{"range":[30,27,30,37],"value":"focalPoint"},"expression":{"range":[30,40,30,54],"value":{"type":"functionOrValue","functionOrValue":{"moduleName":["Point3d"],"name":"origin"}}}}},{"range":[31,27,32,25],"value":{"field":{"range":[31,27,31,35],"value":"eyePoint"},"expression":{"range":[31,38,31,58],"value":{"type":"application","application":[{"range":[31,38,31,52],"value":{"type":"functionOrValue","functionOrValue":{"moduleName":["Point3d"],"name":"meters"}}},{"range":[31,53,31,54],"value":{"type":"integer","integer":5}},{"range":[31,55,31,56],"value":{"type":"integer","integer":2}},{"range":[31,57,31,58],"value":{"type":"integer","integer":3}}]}}}},{"range":[32,27,33,25],"value":{"field":{"range":[32,27,32,38],"value":"upDirection"},"expression":{"range":[32,41,32,62],"value":{"type":"functionOrValue","functionOrValue":{"moduleName":["Direction3d"],"name":"positiveZ"}}}}}]}}]}}}},{"range":[34,19,35,17],"value":{"field":{"range":[34,19,34,38],"value":"verticalFieldOfView"},"expression":{"range":[34,41,34,57],"value":{"type":"application","application":[{"range":[34,41,34,54],"value":{"type":"functionOrValue","functionOrValue":{"moduleName":["Angle"],"name":"degrees"}}},{"range":[34,55,34,57],"value":{"type":"integer","integer":30}}]}}}}]}}]}}}},{"range":[36,11,37,9],"value":{"field":{"range":[36,11,36,20],"value":"clipDepth"},"expression":{"range":[36,23,36,38],"value":{"type":"application","application":[{"range":[36,23,36,36],"value":{"type":"functionOrValue","functionOrValue":{"moduleName":["Length"],"name":"meters"}}},{"range":[36,37,36,38],"value":{"type":"integer","integer":1}}]}}}},{"range":[37,11,38,9],"value":{"field":{"range":[37,11,37,21],"value":"background"},"expression":{"range":[37,24,37,53],"value":{"type":"functionOrValue","functionOrValue":{"moduleName":["Scene3d"],"name":"transparentBackground"}}}}},{"range":[38,11,39,9],"value":{"field":{"range":[38,11,38,21],"value":"dimensions"},"expression":{"range":[38,24,38,64],"value":{"type":"tupled","tupled":[{"range":[38,26,38,43],"value":{"type":"application","application":[{"range":[38,26,38,39],"value":{"type":"functionOrValue","functionOrValue":{"moduleName":["Pixels"],"name":"pixels"}}},{"range":[38,40,38,43],"value":{"type":"integer","integer":800}}]}},{"range":[38,45,38,62],"value":{"type":"application","application":[{"range":[38,45,38,58],"value":{"type":"functionOrValue","functionOrValue":{"moduleName":["Pixels"],"name":"pixels"}}},{"range":[38,59,38,62],"value":{"type":"integer","integer":600}}]}}]}}}}]}}]}}}}}}}],"comments":[]}